{
	"schemaVersion": 1,
	"id": "disable-elytra-flight",
	"version": "${version}",
	"name": "Disable Elytra Flight",
	"description": "Disables Elytra Flight",
	"authors": [
		"Me!"
	],
	"contact": {
		"homepage": "https://fabricmc.net/",
		"sources": "https://github.com/FabricMC/fabric-example-mod"
	},
	"license": "CC0-1.0",
	"icon": "assets/disable-elytra-flight/icon.png",
	"environment": "*",
	"entrypoints": {
		"main": [
			"tjallo.disableelytraflight.DisableElytraFlight"
		]
	},
	"mixins": [
		"disable-elytra-flight.mixins.json"
	],
	"depends": {
		"fabricloader": ">=0.18.4",
		"minecraft": "~1.21.11",
		"java": ">=21",
		"fabric-api": "*"
	}
}